[
    {
        "name": "entity",
        "architectures": [
            {
                "name" : "DDD"
            }
        ]
    },
    {
        "name": "identifier",
        "architectures": [
            {
                "name" : "DDD"
            }
        ]
    },
    {
        "name": "repository",
        "architectures": [
            {
                "name" : "DDD"
            }
        ]
    },
    {
        "name": "validator",
        "architectures": [
            {
                "name" : "DDD"
            }
        ]
    },
    {
        "name": "domainService",
        "architectures": [
            {
                "name" : "DDD"
            }
        ]
    },
    {
        "name": "applicationService",
        "architectures": [
            {
                "name" : "DDD"
            }
        ]
    },
    {
        "name": "resourceController",
        "dependencies": [
            {
                "name" : "applicationService"
            }
        ],
        "architectures": [
            {
                "name" : "REST"
            }
        ]
    }
]